{
	"display": {
		"icon": {
			"item": "iguanatweaksreborn:quartz_arrow"
		},
		"title": {
			"translate": "advancements.sr_story.quartz_arrow.title"
		},
		"description": {
			"translate": "advancements.sr_story.quartz_arrow.description"
		},
		"frame": "task",
		"show_toast": true,
		"announce_to_chat": true,
		"hidden": false
	},
	"parent": "minecraft:story/enter_the_nether",
	"criteria": {
		"quartz_arrow": {
			"trigger": "minecraft:inventory_changed",
			"conditions": {
				"items": [
					{
						"items": [
							"iguanatweaksreborn:quartz_arrow"
						]
					}
				]
			}
		}
	},
	"requirements": [
		[
			"quartz_arrow"
		]
	]
}